DomotApiModbus.py
VmcUnelvent.py
DomotApiModbus/BoilerDedietrich.py
DomotApiModbus/DomotApiModbus.py
DomotApiModbus/VmcUnelvent.py
DomotApiModbus/__init__.py
DomotApiModbus-0.4.0.dist-info/LICENSE
DomotApiModbus-0.4.0.dist-info/METADATA
DomotApiModbus-0.4.0.dist-info/WHEEL
DomotApiModbus-0.4.0.dist-info/top_level.txt
DomotApiModbus-0.4.0.dist-info/RECORD
