Metadata-Version: 2.1
Name: DomotApiModbus
Version: 0.4.0
Summary: Working with modbus devices in domot-api
Home-page: https://github.com/dsacchet/DomotApiModbus
Author: Denis Sacchet
Author-email: denis@sacchet.fr
License: MIT
Keywords: modbus vmc boiler dedietrich unelvent ideo
Platform: UNKNOWN
Classifier: Intended Audience :: Developers
Classifier: Natural Language :: English
Classifier: License :: OSI Approved :: MIT License
Classifier: Programming Language :: Python
Classifier: Programming Language :: Python :: 2.7
Classifier: Topic :: Home Automation
Requires-Dist: minimalmodbus
Requires-Dist: retrying (>=1.3.3)
Requires-Dist: dogpile.cache (>=0.6.2)
